coveriteam/__init__.py
coveriteam/coveriteam.py
coveriteam/example_compositions.py
coveriteam/remote_client.py
coveriteam/util.py
coveriteam/actors/__init__.py
coveriteam/actors/analyzers.py
coveriteam/actors/misc.py
coveriteam/actors/testers.py
coveriteam/artifactlibrary/specifications/coverage-branches.prp
coveriteam/artifactlibrary/specifications/coverage-error-call.prp
coveriteam/artifactlibrary/specifications/coverage-statements.prp
coveriteam/artifactlibrary/specifications/no-overflow.prp
coveriteam/artifactlibrary/specifications/termination.prp
coveriteam/artifactlibrary/specifications/unreach-call.prp
coveriteam/artifactlibrary/specifications/valid-memcleanup.prp
coveriteam/artifactlibrary/specifications/valid-memsafety.prp
coveriteam/interpreter/__init__.py
coveriteam/interpreter/python_code_generator.py
coveriteam/interpreter/utility_visitors.py
coveriteam/language/__init__.py
coveriteam/language/actor.py
coveriteam/language/actorconfig.py
coveriteam/language/artifact.py
coveriteam/language/atomicactor.py
coveriteam/language/composition.py
coveriteam/language/parallel_portfolio.py
coveriteam/language/predmap_join.py
coveriteam/language/utilactors.py
coveriteam/language/witness_join.py
coveriteam/parser/CoVeriLangLexer.py
coveriteam/parser/CoVeriLangParser.py
coveriteam/parser/CoVeriLangVisitor.py
coveriteam/parser/__init__.py
coveriteam/toolconfigs/algo-selector-cst-transform.py
coveriteam/toolconfigs/algo-selector-metaval.py
coveriteam/toolconfigs/classifier-cst-transform.py
coveriteam/toolconfigs/feature-encoder-cst-transform.py
CoVeriTeam-1.0.dist-info/LICENSE
CoVeriTeam-1.0.dist-info/METADATA
CoVeriTeam-1.0.dist-info/WHEEL
CoVeriTeam-1.0.dist-info/entry_points.txt
CoVeriTeam-1.0.dist-info/top_level.txt
CoVeriTeam-1.0.dist-info/RECORD
